<?xml version="1.0" encoding="utf-8"?>
<publishData>
  <publishProfile publishUrl="C:\temp\Deploy\Commander" deleteExistingFiles="False" ftpAnonymousLogin="False" ftpPassiveMode="True" msdeploySite="" msdeploySiteID="" msdeployRemoteSitePhysicalPath="" msdeployAllowUntrustedCertificate="False" msdeploySkipExtraFilesOnServer="True" msdeployMarkAsApp="False" profileName="File System" publishMethod="FileSystem" replaceMatchingFiles="True" userName="" savePWD="False" userPWD="" SelectedForPublish="True">
    <file relUrl="bin/Raven.Client.Lightweight.dll" publishTime="07/18/2012 14:29:07" />
    <file relUrl="bin/Raven.Abstractions.xml" publishTime="07/18/2012 14:29:07" />
    <file relUrl="Views/Arguments/GenerateArgumentsFromBuild.cshtml" publishTime="08/06/2012 10:27:47" />
    <file relUrl="bin/Deploy.Tasks.pdb" publishTime="08/06/2012 11:42:55" />
    <file relUrl="bin/Castle.Windsor.dll" publishTime="02/23/2012 15:01:56" />
    <file relUrl="Global.asax" publishTime="08/06/2012 10:27:47" />
    <file relUrl="Views/_ViewStart.cshtml" publishTime="02/06/2012 14:10:44" />
    <file relUrl="bin/Deploy.Tasks.dll" publishTime="08/06/2012 11:42:56" />
    <file relUrl="Scripts/MicrosoftMvcValidation.js" publishTime="02/06/2012 14:10:44" />
    <file relUrl="Scripts/MicrosoftAjax.js" publishTime="02/06/2012 14:10:44" />
    <file relUrl="bin/Deploy.Commander.dll" publishTime="08/06/2012 13:51:23" />
    <file relUrl="bin/Newtonsoft.Json.pdb" publishTime="02/14/2012 14:06:42" />
    <file relUrl="Scripts/MicrosoftMvcValidation.debug.js" publishTime="02/06/2012 14:10:44" />
    <file relUrl="Scripts/MicrosoftMvcAjax.debug.js" publishTime="02/06/2012 14:10:44" />
    <file relUrl="Views/Shared/Error.cshtml" publishTime="02/06/2012 14:10:44" />
    <file relUrl="bin/Deploy.Procedures.pdb" publishTime="08/06/2012 13:41:07" />
    <file relUrl="bin/Newtonsoft.Json.xml" publishTime="02/14/2012 14:06:42" />
    <file relUrl="Views/Arguments/Create.cshtml" publishTime="08/06/2012 10:27:47" />
    <file relUrl="bin/Raven.Client.Lightweight.pdb" publishTime="07/18/2012 14:29:07" />
    <file relUrl="bin/Deploy.Procedures.dll" publishTime="08/06/2012 13:41:07" />
    <file relUrl="Views/Projects/Open.cshtml" publishTime="08/06/2012 10:27:47" />
    <file relUrl="bin/ICSharpCode.SharpZipLib.dll" publishTime="02/21/2012 15:33:42" />
    <file relUrl="Views/Projects/Index.cshtml" publishTime="08/06/2012 10:27:47" />
    <file relUrl="bin/Castle.Windsor.xml" publishTime="02/23/2012 15:01:56" />
    <file relUrl="Views/Projects/Edit.cshtml" publishTime="08/06/2012 10:27:47" />
    <file relUrl="bin/Castle.Core.dll" publishTime="02/23/2012 15:01:55" />
    <file relUrl="Content/Content.css" publishTime="03/06/2012 14:50:37" />
    <file relUrl="Scripts/jquery.unobtrusive-ajax.min.js" publishTime="02/06/2012 14:10:44" />
    <file relUrl="bin/Castle.Core.xml" publishTime="02/23/2012 15:01:55" />
    <file relUrl="Scripts/pollr.js" publishTime="02/28/2012 14:04:12" />
    <file relUrl="bin/Deploy.Utilities.dll" publishTime="08/06/2012 11:38:08" />
    <file relUrl="bin/Newtonsoft.Json.dll" publishTime="02/14/2012 14:06:42" />
    <file relUrl="Scripts/MicrosoftMvcAjax.js" publishTime="02/06/2012 14:10:44" />
    <file relUrl="Scripts/jquery.validate.unobtrusive.js" publishTime="02/06/2012 14:10:44" />
    <file relUrl="bin/Raven.Client.Lightweight.xml" publishTime="07/18/2012 14:29:07" />
    <file relUrl="Views/Arguments/Edit.cshtml" publishTime="08/06/2012 10:27:47" />
    <file relUrl="Views/Shared/_Layout.cshtml" publishTime="08/06/2012 10:27:47" />
    <file relUrl="bin/Deploy.Utilities.pdb" publishTime="08/06/2012 11:38:08" />
    <file relUrl="bin/NLog.xml" publishTime="07/17/2012 13:49:01" />
    <file relUrl="Views/Builds/Index.cshtml" publishTime="08/06/2012 10:27:47" />
    <file relUrl="bin/Deploy.Commander.Application.dll" publishTime="08/06/2012 13:41:08" />
    <file relUrl="bin/Raven.Abstractions.pdb" publishTime="07/18/2012 14:29:07" />
    <file relUrl="bin/Deploy.Commander.pdb" publishTime="08/06/2012 13:51:23" />
    <file relUrl="Content/Site.css" publishTime="02/06/2012 14:10:44" />
    <file relUrl="bin/Raven.Abstractions.dll" publishTime="07/18/2012 14:29:07" />
    <file relUrl="Scripts/MicrosoftAjax.debug.js" publishTime="02/06/2012 14:10:44" />
    <file relUrl="Views/Web.config" publishTime="02/06/2012 14:10:44" />
    <file relUrl="bin/NLog.dll" publishTime="07/17/2012 13:49:01" />
    <file relUrl="Scripts/jquery.unobtrusive-ajax.js" publishTime="02/06/2012 14:10:44" />
    <file relUrl="Scripts/jquery.validate.unobtrusive.min.js" publishTime="02/06/2012 14:10:44" />
    <file relUrl="bin/Deploy.Commander.Application.pdb" publishTime="08/06/2012 13:41:08" />
    <file relUrl="Web.config" publishTime="08/06/2012 13:56:26" />
  </publishProfile>
</publishData>